{"organisation":"e1e9fda5-cdaa-401b-973b-70edf6124eee","name":"d252200d-084a-4d24-a74d-e5fee5e96847","title":"Workflow result","legal":null,"referenceSystemIdentifier":"EPSG:4283","geoLevel":"NA","key":null,"keyRegex":null,"availability":null,"geomField":"geometry","keyword":null,"theme":null,"temporalExtent":null,"type":null,"_id":null,"bbox":[140.961681984,-38.9096379955,149.976679008,-33.9804255865],"abstract":"","selectedAttributes":[{"name":"geometry","type":"com.vividsolutions.jts.geom.Polygon","title":"geometry","description":"geometry"},{"name":"trainStation","type":"java.lang.Long","title":"trainStation","description":"trainStation"},{"name":"DateMonth","type":"java.lang.Long","title":"DateMonth","description":"DateMonth"},{"name":"DateYear","type":"java.lang.Long","title":"DateYear","description":"DateYear"},{"name":"PropertyCategorisation","type":"java.lang.String","title":"PropertyCategorisation","description":"PropertyCategorisation"},{"name":"SA22011Code","type":"java.lang.Long","title":"SA22011Code","description":"SA22011Code"},{"name":"SA22011Name","type":"java.lang.String","title":"SA22011Name","description":"SA22011Name"},{"name":"feature_code","type":"java.lang.String","title":"feature_code","description":"feature_code"},{"name":"feature_name","type":"java.lang.String","title":"feature_name","description":"feature_name"}],"filter":{"spatial":{"bbox":[140.961681984,-38.9096379955,149.976679008,-33.9804255865]}}}